django_staff-1.2.dist-info/DESCRIPTION.rst
django_staff-1.2.dist-info/METADATA
django_staff-1.2.dist-info/metadata.json
django_staff-1.2.dist-info/pbr.json
django_staff-1.2.dist-info/RECORD
django_staff-1.2.dist-info/top_level.txt
django_staff-1.2.dist-info/WHEEL
example/__init__.py
example/manage.py
example/settings.py
example/urls.py
example/mystaff/__init__.py
example/mystaff/admin.py
example/mystaff/models.py
staff/__init__.py
staff/admin.py
staff/fields.py
staff/forms.py
staff/models.py
staff/settings.py
staff/tests.py
staff/urls.py
staff/views.py
staff/migrations/0001_initial.py
staff/migrations/0002_remove_staffmember_sites.py
staff/migrations/0003_staffmember_title.py
staff/migrations/__init__.py
staff/south_migrations/0001_initial.py
staff/south_migrations/0002_auto__add_field_staffmember_photo_height__add_field_staffmember_photo_.py
staff/south_migrations/0003_auto__add_field_staffmember_facebook__add_field_staffmember_google_plu.py
staff/south_migrations/__init__.py
staff/templates/admin/edit_inline/staff.html
staff/templates/admin/edit_inline/staff13.html
staff/templates/staffmembers/contact.html
staff/templates/staffmembers/contact_done.html
staff/templates/staffmembers/details.html
staff/templates/staffmembers/index.html
staff/templates/staffmembers/story_archive.html
staff/templates/staffmembers/emails/body.txt
staff/templates/staffmembers/emails/subject.txt
