Metadata-Version: 2.0
Name: django-staff
Version: 1.2
Summary: A basic addition to auth.User that manages additional staff info
Home-page: https://github.com/callowayproject/django-staff
Author: Corey Oordt
Author-email: webmaster@callowayproject.com
License: UNKNOWN
Platform: UNKNOWN
Classifier: Framework :: Django
Requires-Dist: django-localflavor-us
